Metadata-Version: 2.1
Name: maxeqx-losowanie-liczby.py
Version: 1.0.2
Summary: Losuje liczbe.
Home-page: 
Author: maxeqx
Author-email: maxeqxmail@gmail.com
License: MIT
Keywords: losuje liczbe
Classifier: Development Status :: 5 - Production/Stable
Classifier: Intended Audience :: Education
Classifier: Operating System :: Microsoft :: Windows :: Windows 10
Classifier: License :: OSI Approved :: MIT License
Classifier: Programming Language :: Python :: 3
License-File: LICENSE.txt
